KinematicSolve/__init__.py
KinematicSolve/kinematicsolvermethods.py
kinematicsolve-3.1.1.dist-info/licenses/LICENSE
kinematicsolve-3.1.1.dist-info/METADATA
kinematicsolve-3.1.1.dist-info/WHEEL
kinematicsolve-3.1.1.dist-info/top_level.txt
kinematicsolve-3.1.1.dist-info/RECORD
