Metadata-Version: 2.4
Name: KinematicSolve
Version: 3.1.1
Summary: An algebra and calculus-based kinematics solver for Python.
Author: Mahir Rahman, Tyler Nguyen
Requires-Python: >=3.8
License-File: LICENSE
Requires-Dist: sympy>=1.11.1
Dynamic: license-file
